src/sem_4/ipa/src/Data_memory.v
module Data_memory (
  input wire Clk,
  input wire [63:0] address,      
  input wire [63:0] Data_write, 
  input wire MemWrite,      
  input wire MemRead,       
  output reg [63:0] Data_read 
);


  reg [7:0] storage [0:1023]; 
  

  integer i;
  initial begin
    for (i = 0; i < 1024; i = i + 1) begin
      storage[i] = 8'd0;  // Initialize all memory to 0
    end
  end
  // Memory write operation (store)
  always @(posedge Clk) begin
    if (MemWrite) begin
    
      storage[address]     <= Data_write[7:0];
      storage[address+1]   <= Data_write[15:8];
      storage[address+2]   <= Data_write[23:16];
      storage[address+3]   <= Data_write[31:24];
      storage[address+4]   <= Data_write[39:32];
      storage[address+5]   <= Data_write[47:40];
      storage[address+6]   <= Data_write[55:48];
      storage[address+7]   <= Data_write[63:56];
    end
  end
  
  // Memory read operation (load)
  always @(*) begin
    if (MemRead) begin
     
      Data_read  = {
        storage[address+7], storage[address+6], storage[address+5], storage[address+4],
        storage[address+3], storage[address+2], storage[address+1], storage[address]
      };
    end else begin
      Data_read = 64'd0;
    end
  end

endmodule

module data_mem(
  input [63:0] write_data,
  input [63:0] address,
  input memorywrite, 
  input clk,
  input memoryread,
  output reg [63:0] read_data,
);

  reg [7:0] mem [63:0]; //memory array
  integer i;

  initial begin
    for (i=0; i<64; i=i+1)
      mem[i] = 0;
    mem[0] = 8'd1;
    mem[8] = 8'd2;
    mem[16] = 8'd3;
    mem[24] = 8'd4;
    mem[32] = 8'd5;
    mem[40] = 8'd6;
    mem[48] = 8'd7;
    mem[56] = 8'd8;
  end

  assign element1 = {mem[7],mem[6],mem[5],mem[4],mem[3],mem[2],mem[1],mem[0]};
  assign element2 = {mem[15],mem[14],mem[13],mem[12],mem[11],mem[10],mem[9],mem[8]};
  assign element3 = {mem[23],mem[22],mem[21],mem[20],mem[19],mem[18],mem[17],mem[16]};
  assign element4 = {mem[31],mem[30],mem[29],mem[28],mem[27],mem[26],mem[25],mem[24]};
  assign element5 = {mem[39],mem[38],mem[37],mem[36],mem[35],mem[34],mem[33],mem[32]};
  assign element6 = {mem[47],mem[46],mem[45],mem[44],mem[43],mem[42],mem[41],mem[40]};
  assign element7 = {mem[55],mem[54],mem[53],mem[52],mem[51],mem[50],mem[49],mem[48]};
  assign element8 = {mem[63],mem[62],mem[61],mem[60],mem[59],mem[58],mem[57],mem[56]};

  always @ (*) begin
    if (memoryread) begin
      read_data[7:0]   = mem[address+0];
      read_data[15:8]  = mem[address+1];
      read_data[23:16] = mem[address+2];
      read_data[31:24] = mem[address+3];
      read_data[39:32] = mem[address+4];
      read_data[47:40] = mem[address+5];
      read_data[55:48] = mem[address+6];
      read_data[63:56] = mem[address+7];
    end
  end

  always @(posedge clk) begin
    if (memorywrite) begin
        mem[address]   = write_data[7:0];
        mem[address+1] = write_data[15:8];
        mem[address+2] = write_data[23:16];
        mem[address+3] = write_data[31:24];
        mem[address+4] = write_data[39:32];
        mem[address+5] = write_data[47:40];
        mem[address+6] = write_data[55:48];
        mem[address+7] = write_data[63:56];
    end
  end

endmodule

src/sem_4/ipa/src/Data_memory_test.v
`timescale 1ns/1ps

module Data_memory_test;

// Testbench signals
reg Clk;
reg [63:0] address;
reg [63:0] Data_write;
reg MemWrite;
reg MemRead;
wire [63:0] Data_read;

// Clock generation (50% duty cycle)
always #5 Clk = ~Clk;

// Instantiate the Data_memory module
Data_memory dut (
    .Clk(Clk),
    .address(address),
    .Data_write(Data_write),
    .MemWrite(MemWrite),
    .MemRead(MemRead),
    .Data_read(Data_read)
);

// Test stimulus
initial begin
    Clk = 0;
    address = 64'h0;
    Data_write = 64'h0;
    MemWrite = 0;
    MemRead = 0;
    
    #20;

    // Test Case 1: Write Operation
    $display("Test Case 1: Write Operation");
    address = 64'h10;  // Byte address (word-aligned)
    Data_write = 64'hABCD_1234_5678_90AB;
    MemWrite = 1;
    MemRead = 0;
    #10;
    MemWrite = 0; // Stop writing

    // Test Case 2: Read Operation (Reading previously written data)
    #10;
    $display("Test Case 2: Read Operation");
    MemRead = 1;
    #10;
    if (Data_read === 64'hABCD_1234_5678_90AB)
        $display("Read Test Passed: Expected value matches read value");
    else
        $display("Read Test Failed: Expected %h, got %h", 64'hABCD_1234_5678_90AB, Data_read);
    MemRead = 0;

    // Test Case 3: Write to different location
    #10;
    $display("Test Case 3: Write to different location");
    address = 64'h20;  // Word-aligned
    Data_write = 64'hFFFF_0000_AAAA_5555;
    MemWrite = 1;
    #10;
    MemWrite = 0;

    // Test Case 4: Read from new location
    #10;
    $display("Test Case 4: Read from new location");
    MemRead = 1;
    #10;
    if (Data_read === 64'hFFFF_0000_AAAA_5555)
        $display("Read Test Passed: Expected value matches read value");
    else
        $display("Read Test Failed: Expected %h, got %h", 64'hFFFF_0000_AAAA_5555, Data_read);
    MemRead = 0;

    // Test Case 5: Read with MemRead disabled
    #10;
    $display("Test Case 5: Read with MemRead disabled");
    #10;
    if (Data_read === 64'h0)
        $display("Disabled Read Test Passed: Output is zero when MemRead is disabled");
    else
        $display("Disabled Read Test Failed: Expected 0, got %h", Data_read);

    // Test Case 6: Write and Read from boundary address
    #10;
    $display("Test Case 6: Write and Read from boundary address");
    address = 64'hFF;  // Last valid address
    Data_write = 64'h1111_2222_3333_4444;
    MemWrite = 1;
    MemRead = 0;
    #10;
    MemWrite = 0;
    MemRead = 1;
    #10;
    if (Data_read === 64'h1111_2222_3333_4444)
        $display("Boundary Test Passed: Expected value matches read value");
    else
        $display("Boundary Test Failed: Expected %h, got %h", 64'h1111_2222_3333_4444, Data_read);
    
    #100;
   
    $finish;
end

initial begin
    $dumpfile("data_memory_test.vcd");
    $dumpvars(0, Data_memory_test);
end

endmodule

src/sem_4/ipa/src/data_memory_test.vcd
$date
	Mon Mar  3 19:24:48 2025
$end
$version
	Icarus Verilog
$end
$timescale
	1ps
$end
$scope module Data_memory_test $end
$var wire 64 ! Data_read [63:0] $end
$var reg 1 " Clk $end
$var reg 64 # Data_write [63:0] $end
$var reg 1 $ MemRead $end
$var reg 1 % MemWrite $end
$var reg 64 & address [63:0] $end
$scope module dut $end
$var wire 1 " Clk $end
$var wire 64 ' Data_write [63:0] $end
$var wire 1 $ MemRead $end
$var wire 1 % MemWrite $end
$var wire 64 ( address [63:0] $end
$var reg 64 ) Data_read [63:0] $end
$var integer 32 * i [31:0] $end
$upscope $end
$upscope $end
$enddefinitions $end
#0
$dumpvars
b10000000000 *
b0 )
b0 (
b0 '
b0 &
0%
0$
b0 #
0"
b0 !
$end
#5000
1"
#10000
0"
#15000
1"
#20000
0"
1%
b1010101111001101000100100011010001010110011110001001000010101011 #
b1010101111001101000100100011010001010110011110001001000010101011 '
b10000 &
b10000 (
#25000
1"
#30000
0"
0%
#35000
1"
#40000
b1010101111001101000100100011010001010110011110001001000010101011 !
b1010101111001101000100100011010001010110011110001001000010101011 )
0"
1$
#45000
1"
#50000
b0 !
b0 )
0"
0$
#55000
1"
#60000
0"
1%
b1111111111111111000000000000000010101010101010100101010101010101 #
b1111111111111111000000000000000010101010101010100101010101010101 '
b100000 &
b100000 (
#65000
1"
#70000
0"
0%
#75000
1"
#80000
b1111111111111111000000000000000010101010101010100101010101010101 !
b1111111111111111000000000000000010101010101010100101010101010101 )
0"
1$
#85000
1"
#90000
b0 !
b0 )
0"
0$
#95000
1"
#100000
0"
#105000
1"
#110000
0"
#115000
1"
#120000
0"
1%
b1000100010001001000100010001000110011001100110100010001000100 #
b1000100010001001000100010001000110011001100110100010001000100 '
b11111111 &
b11111111 (
#125000
1"
#130000
b1000100010001001000100010001000110011001100110100010001000100 !
b1000100010001001000100010001000110011001100110100010001000100 )
0"
1$
0%
