src/sem_4/ipa/all.v
// ======================================================
// RISC-V Processor (Single-Cycle) with 64-bit ALU
// ======================================================
module riscv_processor(
    input wire clk,
    input wire rst
);
    // Program Counter
    reg [31:0] pc;
    wire [31:0] next_pc;
    
    // Instruction Memory
    reg [31:0] instr_mem [0:1023];
    wire [31:0] instruction = instr_mem[pc >> 2];
    
    // Control Signals
    wire RegWrite, MemRead, MemWrite, MemtoReg, ALUSrc, Branch, Jump;
    wire [1:0] ALUOp;
    wire [3:0] ALUControl;
    
    // Control Unit
    control_unit control(
        .opcode(instruction[6:0]),
        .Branch(Branch),
        .Jump(Jump),
        .RegWrite(RegWrite),
        .MemRead(MemRead),
        .MemWrite(MemWrite),
        .MemtoReg(MemtoReg),
        .ALUSrc(ALUSrc),
        .ALUOp(ALUOp)
    );
    
    // ALU Control
    alu_control alu_ctrl(
        .ALUOp(ALUOp),
        .funct3(instruction[14:12]),
        .funct7(instruction[31:25]),
        .alu_control(ALUControl)
    );
    
    // Register File
    reg [63:0] registers [0:31]; // Updated to 64-bit registers
    wire [4:0] rs1 = instruction[19:15];
    wire [4:0] rs2 = instruction[24:20];
    wire [4:0] rd = instruction[11:7];
    wire [63:0] read_data1 = registers[rs1];
    wire [63:0] read_data2 = registers[rs2];
    
    // Immediate Generator
    wire [63:0] imm_gen;
    immediate_generator imm_gen_module(
        .instruction(instruction),
        .immediate(imm_gen)
    );
    
    // ALU (64-bit)
    wire [63:0] alu_in2 = ALUSrc ? imm_gen : read_data2;
    wire [63:0] alu_result;
    wire zero;
    ALU my_alu(
        .control(ALUControl),
        .a(read_data1),
        .b(alu_in2),
        .result(alu_result),
        .zero(zero)
    );
    
    // Branch Logic
    wire branch_taken;
    branch_decision branch_dec(
        .funct3(instruction[14:12]),
        .zero(zero),
        .branch(branch_taken)
    );
    
    // Next PC
    wire [31:0] branch_target = pc + imm_gen[31:0];
    wire [31:0] jump_target = pc + imm_gen[31:0];
    assign next_pc = Jump                ? jump_target :      // JAL/JALR
                    (Branch & branch_taken) ? branch_target : // Branches
                    pc + 4;                                   // Default
    
    // Data Memory
    reg [63:0] data_mem [0:1023]; // Updated to 64-bit memory
    wire [63:0] mem_data = MemRead ? data_mem[alu_result >> 2] : 0;
    wire [63:0] write_data = MemtoReg ? mem_data : alu_result;
    
    // Update State
    always @(posedge clk or posedge rst) begin
        if(rst) begin
            pc <= 0;
            for(integer i = 0; i < 32; i++) registers[i] <= 0;
        end else begin
            pc <= next_pc;
            if(RegWrite && rd != 0) registers[rd] <= write_data;
            if(MemWrite) data_mem[alu_result >> 2] <= read_data2;
        end
    end
endmodule

// ======================================================
// Control Unit
// ======================================================
module control_unit(
    input wire [6:0] opcode,
    output reg Branch, Jump,
    output reg RegWrite, MemRead, MemWrite, MemtoReg, ALUSrc,
    output reg [1:0] ALUOp
);
    always @(*) begin
        RegWrite = 0; MemRead = 0; MemWrite = 0;
        MemtoReg = 0; ALUSrc = 0; ALUOp = 2'b00;
        Branch = 0; Jump = 0;
        
        case(opcode)
            7'b0110011: begin RegWrite=1; ALUOp=2'b10; end        // R-type
            7'b0010011: begin RegWrite=1; ALUSrc=1; ALUOp=2'b11; end // I-type
            7'b0000011: begin RegWrite=1; ALUSrc=1; MemRead=1; MemtoReg=1; end // Load
            7'b0100011: begin ALUSrc=1; MemWrite=1; end            // Store
            7'b1100011: begin Branch=1; ALUOp=2'b01; end           // Branch
            7'b1101111: begin // JAL
                RegWrite = 1;
                Jump = 1;
            end
            7'b1100111: begin // JALR
                RegWrite = 1;
                Jump = 1;
                ALUSrc = 1;
                ALUOp = 2'b00; // ADD for address calculation
            end
            default: ; 
        endcase
    end
endmodule

// ======================================================
// ALU Control
// ======================================================
module alu_control(
    input wire [1:0] ALUOp,
    input wire [2:0] funct3,
    input wire [6:0] funct7,
    output reg [3:0] alu_control
);
    always @(*) begin
        case(ALUOp)
            2'b00: alu_control = 4'b0000;  // ADD
            2'b01: alu_control = 4'b0001;  // SUB
            2'b10: begin  // R-type
                case(funct3)
                    3'b000: alu_control = funct7[5] ? 4'b0001 : 4'b0000;  // SUB/ADD
                    3'b001: alu_control = 4'b0111;  // SLL
                    default: alu_control = 4'b0000;
                endcase
            end
            2'b11: begin  // I-type
                case(funct3)
                    3'b000: alu_control = 4'b0000;  // ADDI
                    3'b001: alu_control = 4'b0111;  // SLLI
                    default: alu_control = 4'b0000;
                endcase
            end
            default: alu_control = 4'b0000;
        endcase
    end
endmodule

// ======================================================
// Immediate Generator
// ======================================================
module immediate_generator(
    input wire [31:0] instruction,
    output reg [63:0] immediate
);
    always @(*) begin
        case(instruction[6:0])
            7'b0010011,7'b0000011: // I-type
                immediate = {{52{instruction[31]}}, instruction[31:20]};
            7'b0100011: // S-type
                immediate = {{52{instruction[31]}}, instruction[31:25], instruction[11:7]};
            7'b1100011: // B-type
                immediate = {{51{instruction[31]}}, instruction[31], instruction[7], 
                           instruction[30:25], instruction[11:8], 1'b0};
            7'b1101111: // JAL (UJ-type)
                immediate = { {44{instruction[31]}}, instruction[31], instruction[19:12], 
                           instruction[20], instruction[30:21], 1'b0 };
            default: immediate = 0;
        endcase
    end
endmodule

// ======================================================
// Branch Decision
// ======================================================
module branch_decision(
    input wire [2:0] funct3,
    input wire zero,
    output reg branch
);
    always @(*) begin
        case(funct3)
            3'b000: branch = zero;   // BEQ
            3'b001: branch = ~zero;  // BNE
            default: branch = 0;
        endcase
    end
endmodule

// ======================================================
// ALU (64-bit)
// ======================================================
module ALU(
    input wire [3:0] control,
    input wire [63:0] a,
    input wire [63:0] b,
    output reg [63:0] result,
    output reg zero
);
    // ALU Operations
    parameter ADD  = 4'b0000;
    parameter SUB  = 4'b0001;
    parameter SLT  = 4'b0010;
    parameter SLTU = 4'b0011;
    parameter AND  = 4'b0100;
    parameter OR   = 4'b0101;
    parameter XOR  = 4'b0110;
    parameter SLL  = 4'b0111;
    parameter SRL  = 4'b1000;
    parameter SRA  = 4'b1001;
    parameter BEQ  = 4'b1010;

    always @(*) begin
        case(control)
            ADD:  result = a + b;
            SUB:  result = a - b;
            SLT:  result = ($signed(a) < $signed(b)) ? 64'b1 : 64'b0;
            SLTU: result = (a < b) ? 64'b1 : 64'b0;
            AND:  result = a & b;
            OR:   result = a | b;
            XOR:  result = a ^ b;
            SLL:  result = a << b[5:0];
            SRL:  result = a >> b[5:0];
            SRA:  result = $signed(a) >>> b[5:0];
            BEQ:  result = (a == b) ? 64'b1 : 64'b0;
            default: result = 0;
        endcase
        zero = (result == 0);
    end
endmodule

src/sem_4/ipa/all_tb.v
`timescale 1ns/1ps

module riscv_processor_tb;

    // Inputs
    reg clk;
    reg rst;

    // Instantiate the processor
    riscv_processor uut (
        .clk(clk),
        .rst(rst)
    );

    // Clock generation
    initial begin
        clk = 0;
        forever #5 clk = ~clk; // 10ns clock period
    end

    // Test sequence
    initial begin
        // Initialize memory with test program
        uut.instr_mem[0] = 32'h002081b3; // ADD x3, x1, x2
        uut.instr_mem[1] = 32'h40308233; // SUB x4, x1, x3
        uut.instr_mem[2] = 32'h0041a023; // SW x4, 0(x3)
        uut.instr_mem[3] = 32'h0001a203; // LW x4, 0(x3)
        uut.instr_mem[4] = 32'h00418263; // BEQ x3, x4, 4
        uut.instr_mem[5] = 32'h00c000ef; // JAL x1, 12
        uut.instr_mem[6] = 32'h00000013; // NOP
        uut.instr_mem[7] = 32'h00000013; // NOP

        // Initialize registers
        uut.registers[1] = 32'h00000005; // x1 = 5
        uut.registers[2] = 32'h00000003; // x2 = 3

        // Reset the processor
        rst = 1;
        #20;
        rst = 0;

        // Run for 100 clock cycles
        #1000;

        // Display final register values
        $display("Final Register Values:");
        for (integer i = 0; i < 32; i = i + 1) begin
            $display("x%0d = %h", i, uut.registers[i]);
        end

        // Display memory contents
        $display("Memory Contents:");
        for (integer i = 0; i < 10; i = i + 1) begin
            $display("Mem[%0d] = %h", i, uut.data_mem[i]);
        end

        // End simulation
        $finish;
    end

    // VCD dump file generation
    initial begin
        $dumpfile("riscv_processor_tb.vcd");
        $dumpvars(0, riscv_processor_tb);
    end

endmodule

src/sem_4/ipa/riscv_processor_tb.vcd
$date
	Tue Mar  4 01:40:23 2025
$end
$version
	Icarus Verilog
$end
$timescale
	1ps
$end
$scope module riscv_processor_tb $end
$var reg 1 ! clk $end
$var reg 1 " rst $end
$scope module uut $end
$var wire 1 ! clk $end
$var wire 32 # instruction [31:0] $end
$var wire 64 $ read_data1 [63:0] $end
$var wire 64 % read_data2 [63:0] $end
$var wire 1 " rst $end
$var wire 1 & zero $end
$var wire 64 ' write_data [63:0] $end
$var wire 5 ( rs2 [4:0] $end
$var wire 5 ) rs1 [4:0] $end
$var wire 5 * rd [4:0] $end
$var wire 32 + next_pc [31:0] $end
$var wire 64 , mem_data [63:0] $end
$var wire 32 - jump_target [31:0] $end
$var wire 64 . imm_gen [63:0] $end
$var wire 32 / branch_target [31:0] $end
$var wire 1 0 branch_taken $end
$var wire 64 1 alu_result [63:0] $end
$var wire 64 2 alu_in2 [63:0] $end
$var wire 1 3 RegWrite $end
$var wire 1 4 MemtoReg $end
$var wire 1 5 MemWrite $end
$var wire 1 6 MemRead $end
$var wire 1 7 Jump $end
$var wire 1 8 Branch $end
$var wire 1 9 ALUSrc $end
$var wire 2 : ALUOp [1:0] $end
$var wire 4 ; ALUControl [3:0] $end
$var reg 32 < pc [31:0] $end
$scope module alu_ctrl $end
$var wire 3 = funct3 [2:0] $end
$var wire 7 > funct7 [6:0] $end
$var wire 2 ? ALUOp [1:0] $end
$var reg 4 @ alu_control [3:0] $end
$upscope $end
$scope module branch_dec $end
$var wire 3 A funct3 [2:0] $end
$var wire 1 & zero $end
$var reg 1 0 branch $end
$upscope $end
$scope module control $end
$var wire 7 B opcode [6:0] $end
$var reg 2 C ALUOp [1:0] $end
$var reg 1 9 ALUSrc $end
$var reg 1 8 Branch $end
$var reg 1 7 Jump $end
$var reg 1 6 MemRead $end
$var reg 1 5 MemWrite $end
$var reg 1 4 MemtoReg $end
$var reg 1 3 RegWrite $end
$upscope $end
$scope module imm_gen_module $end
$var wire 32 D instruction [31:0] $end
$var reg 64 E immediate [63:0] $end
$upscope $end
$scope module my_alu $end
$var wire 64 F a [63:0] $end
$var wire 64 G b [63:0] $end
$var wire 4 H control [3:0] $end
$var reg 64 I result [63:0] $end
$var reg 1 & zero $end
$upscope $end
$scope begin $ivl_for_loop2 $end
$var integer 32 J i [31:0] $end
$upscope $end
$upscope $end
$scope begin $ivl_for_loop0 $end
$var integer 32 K i [31:0] $end
$upscope $end
$scope begin $ivl_for_loop1 $end
$var integer 32 L i [31:0] $end
$upscope $end
$upscope $end
$enddefinitions $end
#0
$dumpvars
bx L
bx K
b100000 J
b0 I
b0 H
b0 G
b0 F
b0 E
b1000001000000110110011 D
b10 C
b110011 B
b0 A
b0 @
b10 ?
b0 >
b0 =
b0 <
b0 ;
b10 :
09
08
07
06
05
04
13
b0 2
b0 1
10
b0 /
b0 .
b0 -
b0 ,
b100 +
b11 *
b1 )
b10 (
b0 '
1&
b0 %
b0 $
b1000001000000110110011 #
1"
0!
$end
#5000
b100000 J
1!
#10000
0!
#15000
b100000 J
1!
#20000
0!
0"
#25000
b1 ;
b1 @
b1 H
b100000 >
b11 (
b100 *
b1000 +
b1000000001100001000001000110011 #
b1000000001100001000001000110011 D
b100 /
b100 -
b100 <
1!
#30000
0!
#35000
15
19
b0 :
b0 ?
b0 C
03
b0 ;
b0 @
b0 H
00
b100011 B
b10 =
b0 >
b11 )
b100 (
b0 *
b10 A
b1100 +
b10000011010000000100011 #
b10000011010000000100011 D
b1000 /
b1000 -
b1000 <
1!
#40000
0!
#45000
14
16
13
19
05
b11 B
b0 (
b100 *
b10000 +
b11010001000000011 #
b11010001000000011 D
b1100 /
b1100 -
b1100 <
1!
#50000
0!
#55000
b1 ;
b1 @
b1 H
b0 '
1&
b0 1
b0 I
b1 :
b1 ?
b1 C
18
09
04
06
03
10
b0 2
b0 G
b1100011 B
b0 =
b100 (
b0 A
b100 .
b100 E
b10100 +
b10000011000001001100011 #
b10000011000001001100011 D
b10100 /
b10100 -
b10000 <
1!
#60000
0!
#65000
b0 ;
b0 @
b0 H
17
13
08
b0 :
b0 ?
b0 C
b1101111 B
b0 )
b1100 (
b1 *
b1100 .
b1100 E
b100000 +
b110000000000000011101111 #
b110000000000000011101111 D
b100000 /
b100000 -
b10100 <
1!
#70000
0!
#75000
bx '
07
03
x&
bx 1
bx I
bx 2
bx G
00
bx B
bx =
bx >
bx $
bx F
bx )
bx %
bx (
bx *
bx A
b0 .
b0 E
bx #
bx D
b100100 +
b100000 /
b100000 -
b100000 <
1!
#80000
0!
#85000
b101000 +
b100100 /
b100100 -
b100100 <
1!
#90000
0!
#95000
b101100 +
b101000 /
b101000 -
b101000 <
1!
#100000
0!
#105000
b110000 +
b101100 /
b101100 -
b101100 <
1!
#110000
0!
#115000
b110100 +
b110000 /
b110000 -
b110000 <
1!
#120000
0!
#125000
b111000 +
b110100 /
b110100 -
b110100 <
1!
#130000
0!
#135000
b111100 +
b111000 /
b111000 -
b111000 <
1!
#140000
0!
#145000
b1000000 +
b111100 /
b111100 -
b111100 <
1!
#150000
0!
#155000
b1000100 +
b1000000 /
b1000000 -
b1000000 <
1!
#160000
0!
#165000
b1001000 +
b1000100 /
b1000100 -
b1000100 <
1!
#170000
0!
#175000
b1001100 +
b1001000 /
b1001000 -
b1001000 <
1!
#180000
0!
#185000
b1010000 +
b1001100 /
b1001100 -
b1001100 <
1!
#190000
0!
#195000
b1010100 +
b1010000 /
b1010000 -
b1010000 <
1!
#200000
0!
#205000
b1011000 +
b1010100 /
b1010100 -
b1010100 <
1!
#210000
0!
#215000
b1011100 +
b1011000 /
b1011000 -
b1011000 <
1!
#220000
0!
#225000
b1100000 +
b1011100 /
b1011100 -
b1011100 <
1!
#230000
0!
#235000
b1100100 +
b1100000 /
b1100000 -
b1100000 <
1!
#240000
0!
#245000
b1101000 +
b1100100 /
b1100100 -
b1100100 <
1!
#250000
0!
#255000
b1101100 +
b1101000 /
b1101000 -
b1101000 <
1!
#260000
0!
#265000
b1110000 +
b1101100 /
b1101100 -
b1101100 <
1!
#270000
0!
#275000
b1110100 +
b1110000 /
b1110000 -
b1110000 <
1!
#280000
0!
#285000
b1111000 +
b1110100 /
b1110100 -
b1110100 <
1!
#290000
0!
#295000
b1111100 +
b1111000 /
b1111000 -
b1111000 <
1!
#300000
0!
#305000
b10000000 +
b1111100 /
b1111100 -
b1111100 <
1!
#310000
0!
#315000
b10000100 +
b10000000 /
b10000000 -
b10000000 <
1!
#320000
0!
#325000
b10001000 +
b10000100 /
b10000100 -
b10000100 <
1!
#330000
0!
#335000
b10001100 +
b10001000 /
b10001000 -
b10001000 <
1!
#340000
0!
#345000
b10010000 +
b10001100 /
b10001100 -
b10001100 <
1!
#350000
0!
#355000
b10010100 +
b10010000 /
b10010000 -
b10010000 <
1!
#360000
0!
#365000
b10011000 +
b10010100 /
b10010100 -
b10010100 <
1!
#370000
0!
#375000
b10011100 +
b10011000 /
b10011000 -
b10011000 <
1!
#380000
0!
#385000
b10100000 +
b10011100 /
b10011100 -
b10011100 <
1!
#390000
0!
#395000
b10100100 +
b10100000 /
b10100000 -
b10100000 <
1!
#400000
0!
#405000
b10101000 +
b10100100 /
b10100100 -
b10100100 <
1!
#410000
0!
#415000
b10101100 +
b10101000 /
b10101000 -
b10101000 <
1!
#420000
0!
#425000
b10110000 +
b10101100 /
b10101100 -
b10101100 <
1!
#430000
0!
#435000
b10110100 +
b10110000 /
b10110000 -
b10110000 <
1!
#440000
0!
#445000
b10111000 +
b10110100 /
b10110100 -
b10110100 <
1!
#450000
0!
#455000
b10111100 +
b10111000 /
b10111000 -
b10111000 <
1!
#460000
0!
#465000
b11000000 +
b10111100 /
b10111100 -
b10111100 <
1!
#470000
0!
#475000
b11000100 +
b11000000 /
b11000000 -
b11000000 <
1!
#480000
0!
#485000
b11001000 +
b11000100 /
b11000100 -
b11000100 <
1!
#490000
0!
#495000
b11001100 +
b11001000 /
b11001000 -
b11001000 <
1!
#500000
0!
#505000
b11010000 +
b11001100 /
b11001100 -
b11001100 <
1!
#510000
0!
#515000
b11010100 +
b11010000 /
b11010000 -
b11010000 <
1!
#520000
0!
#525000
b11011000 +
b11010100 /
b11010100 -
b11010100 <
1!
#530000
0!
#535000
b11011100 +
b11011000 /
b11011000 -
b11011000 <
1!
#540000
0!
#545000
b11100000 +
b11011100 /
b11011100 -
b11011100 <
1!
#550000
0!
#555000
b11100100 +
b11100000 /
b11100000 -
b11100000 <
1!
#560000
0!
#565000
b11101000 +
b11100100 /
b11100100 -
b11100100 <
1!
#570000
0!
#575000
b11101100 +
b11101000 /
b11101000 -
b11101000 <
1!
#580000
0!
#585000
b11110000 +
b11101100 /
b11101100 -
b11101100 <
1!
#590000
0!
#595000
b11110100 +
b11110000 /
b11110000 -
b11110000 <
1!
#600000
0!
#605000
b11111000 +
b11110100 /
b11110100 -
b11110100 <
1!
#610000
0!
#615000
b11111100 +
b11111000 /
b11111000 -
b11111000 <
1!
#620000
0!
#625000
b100000000 +
b11111100 /
b11111100 -
b11111100 <
1!
#630000
0!
#635000
b100000100 +
b100000000 /
b100000000 -
b100000000 <
1!
#640000
0!
#645000
b100001000 +
b100000100 /
b100000100 -
b100000100 <
1!
#650000
0!
#655000
b100001100 +
b100001000 /
b100001000 -
b100001000 <
1!
#660000
0!
#665000
b100010000 +
b100001100 /
b100001100 -
b100001100 <
1!
#670000
0!
#675000
b100010100 +
b100010000 /
b100010000 -
b100010000 <
1!
#680000
0!
#685000
b100011000 +
b100010100 /
b100010100 -
b100010100 <
1!
#690000
0!
#695000
b100011100 +
b100011000 /
b100011000 -
b100011000 <
1!
#700000
0!
#705000
b100100000 +
b100011100 /
b100011100 -
b100011100 <
1!
#710000
0!
#715000
b100100100 +
b100100000 /
b100100000 -
b100100000 <
1!
#720000
0!
#725000
b100101000 +
b100100100 /
b100100100 -
b100100100 <
1!
#730000
0!
#735000
b100101100 +
b100101000 /
b100101000 -
b100101000 <
1!
#740000
0!
#745000
b100110000 +
b100101100 /
b100101100 -
b100101100 <
1!
#750000
0!
#755000
b100110100 +
b100110000 /
b100110000 -
b100110000 <
1!
#760000
0!
#765000
b100111000 +
b100110100 /
b100110100 -
b100110100 <
1!
#770000
0!
#775000
b100111100 +
b100111000 /
b100111000 -
b100111000 <
1!
#780000
0!
#785000
b101000000 +
b100111100 /
b100111100 -
b100111100 <
1!
#790000
0!
#795000
b101000100 +
b101000000 /
b101000000 -
b101000000 <
1!
#800000
0!
#805000
b101001000 +
b101000100 /
b101000100 -
b101000100 <
1!
#810000
0!
#815000
b101001100 +
b101001000 /
b101001000 -
b101001000 <
1!
#820000
0!
#825000
b101010000 +
b101001100 /
b101001100 -
b101001100 <
1!
#830000
0!
#835000
b101010100 +
b101010000 /
b101010000 -
b101010000 <
1!
#840000
0!
#845000
b101011000 +
b101010100 /
b101010100 -
b101010100 <
1!
#850000
0!
#855000
b101011100 +
b101011000 /
b101011000 -
b101011000 <
1!
#860000
0!
#865000
b101100000 +
b101011100 /
b101011100 -
b101011100 <
1!
#870000
0!
#875000
b101100100 +
b101100000 /
b101100000 -
b101100000 <
1!
#880000
0!
#885000
b101101000 +
b101100100 /
b101100100 -
b101100100 <
1!
#890000
0!
#895000
b101101100 +
b101101000 /
b101101000 -
b101101000 <
1!
#900000
0!
#905000
b101110000 +
b101101100 /
b101101100 -
b101101100 <
1!
#910000
0!
#915000
b101110100 +
b101110000 /
b101110000 -
b101110000 <
1!
#920000
0!
#925000
b101111000 +
b101110100 /
b101110100 -
b101110100 <
1!
#930000
0!
#935000
b101111100 +
b101111000 /
b101111000 -
b101111000 <
1!
#940000
0!
#945000
b110000000 +
b101111100 /
b101111100 -
b101111100 <
1!
#950000
0!
#955000
b110000100 +
b110000000 /
b110000000 -
b110000000 <
1!
#960000
0!
#965000
b110001000 +
b110000100 /
b110000100 -
b110000100 <
1!
#970000
0!
#975000
b110001100 +
b110001000 /
b110001000 -
b110001000 <
1!
#980000
0!
#985000
b110010000 +
b110001100 /
b110001100 -
b110001100 <
1!
#990000
0!
#995000
b110010100 +
b110010000 /
b110010000 -
b110010000 <
1!
#1000000
0!
#1005000
b110011000 +
b110010100 /
b110010100 -
b110010100 <
1!
#1010000
0!
#1015000
b110011100 +
b110011000 /
b110011000 -
b110011000 <
1!
#1020000
0!
b1010 L
b100000 K
